pdiary/__init__.py
pdiary/forms.py
pdiary/main.py
pdiary/lib/database.py
pdiary/lib/utils.py
pdiary-0.80.1.dist-info/METADATA
pdiary-0.80.1.dist-info/RECORD
pdiary-0.80.1.dist-info/WHEEL
pdiary-0.80.1.dist-info/entry_points.txt
pdiary-0.80.1.dist-info/top_level.txt
